mcp_server_flyder/__init__.py
mcp_server_flyder/server.py
mcp_server_flyder-0.4.5.dist-info/METADATA
mcp_server_flyder-0.4.5.dist-info/WHEEL
mcp_server_flyder-0.4.5.dist-info/entry_points.txt
mcp_server_flyder-0.4.5.dist-info/licenses/LICENSE
mcp_server_flyder-0.4.5.dist-info/RECORD
