Metadata-Version: 2.4
Name: mcp-server-flyder
Version: 0.4.5
Summary: MCP Server for Flyder
Author-email: Bill Antoniadis <bill.antoniadis@streamline.us>
License-File: LICENSE
Requires-Python: >=3.12
Requires-Dist: httpx>=0.28.1
Requires-Dist: mcp[cli]>=1.6.0
